vaisala_pymodbus/__init__.py
vaisala_pymodbus/cli.py
vaisala_pymodbus/vaisala_pymodbus.py
vaisala_pymodbus-0.1.0.dist-info/AUTHORS.rst
vaisala_pymodbus-0.1.0.dist-info/LICENSE
vaisala_pymodbus-0.1.0.dist-info/METADATA
vaisala_pymodbus-0.1.0.dist-info/WHEEL
vaisala_pymodbus-0.1.0.dist-info/top_level.txt
vaisala_pymodbus-0.1.0.dist-info/RECORD
