Metadata-Version: 2.1
Name: vaisala_pymodbus
Version: 0.1.0
Summary: Interface for Vaisala instruments for Python environment using Modbus protocol
Author-email: Julius Oskar Schaaf <julius.schaaf@gmail.com>
Maintainer-email: Julius Oskar Schaaf <julius.schaaf@gmail.com>
License: MIT license
Project-URL: bugs, https://github.com/OScurry/vaisala_pymodbus/issues
Project-URL: changelog, https://github.com/OScurry/vaisala_pymodbus/blob/master/changelog.md
Project-URL: homepage, https://github.com/OScurry/vaisala_pymodbus
License-File: LICENSE
License-File: AUTHORS.rst
Requires-Dist: typer
Provides-Extra: dev
Requires-Dist: coverage ; extra == 'dev'
Requires-Dist: mypy ; extra == 'dev'
Requires-Dist: pytest ; extra == 'dev'
Requires-Dist: ruff ; extra == 'dev'
